mockflow/__init__.py
mockflow/core.py
mockflow/models.py
mockflow/scenarios.py
mockflow/utils.py
mockflow-0.1.0.dist-info/METADATA
mockflow-0.1.0.dist-info/WHEEL
mockflow-0.1.0.dist-info/licenses/LICENSE
mockflow-0.1.0.dist-info/RECORD
