Metadata-Version: 2.4
Name: mockflow
Version: 0.1.0
Summary: Professional-grade financial time series mock data generation
Project-URL: Homepage, https://github.com/stefan-mcf/conflux-ml-engine
Project-URL: Repository, https://github.com/stefan-mcf/conflux-ml-engine
Project-URL: Issues, https://github.com/stefan-mcf/conflux-ml-engine/issues
Author: Conflux ML Engine Team
License: MIT
License-File: LICENSE
Classifier: Development Status :: 4 - Beta
Classifier: Intended Audience :: Developers
Classifier: Intended Audience :: Financial and Insurance Industry
Classifier: License :: OSI Approved :: MIT License
Classifier: Programming Language :: Python :: 3
Classifier: Programming Language :: Python :: 3.8
Classifier: Programming Language :: Python :: 3.9
Classifier: Programming Language :: Python :: 3.10
Classifier: Programming Language :: Python :: 3.11
Classifier: Topic :: Office/Business :: Financial
Classifier: Topic :: Scientific/Engineering :: Mathematics
Requires-Python: >=3.8
Requires-Dist: numpy>=1.20.0
Requires-Dist: pandas>=1.3.0
Provides-Extra: dev
Requires-Dist: black; extra == 'dev'
Requires-Dist: mypy; extra == 'dev'
Requires-Dist: pandas-stubs; extra == 'dev'
Requires-Dist: pytest-cov; extra == 'dev'
Requires-Dist: pytest>=7.0; extra == 'dev'
Requires-Dist: ruff; extra == 'dev'
Requires-Dist: types-requests; extra == 'dev'
